LICENSE
README.md
docs/Makefile
docs/make.bat
docs/source/api/knit_graphs.Course.rst
docs/source/api/knit_graphs.Knit_Graph.rst
docs/source/api/knit_graphs.Knit_Graph_Visualizer.rst
docs/source/api/knit_graphs.Loop.rst
docs/source/api/knit_graphs.Pull_Direction.rst
docs/source/api/knit_graphs.Yarn.rst
docs/source/api/knit_graphs.artin_wale_braids.Crossing_Direction.rst
docs/source/api/knit_graphs.artin_wale_braids.Loop_Braid_Graph.rst
docs/source/api/knit_graphs.artin_wale_braids.Wale.rst
docs/source/api/knit_graphs.artin_wale_braids.Wale_Braid.rst
docs/source/api/knit_graphs.artin_wale_braids.Wale_Braid_Word.rst
docs/source/api/knit_graphs.artin_wale_braids.Wale_Group.rst
docs/source/api/knit_graphs.artin_wale_braids.rst
docs/source/api/knit_graphs.basic_knit_graph_generators.rst
docs/source/api/knit_graphs.rst
docs/source/conf.py
docs/source/index.rst
docs/source/installation.rst
knit_graphs/Course.py
knit_graphs/Knit_Graph.py
knit_graphs/Knit_Graph_Visualizer.py
knit_graphs/Loop.py
knit_graphs/Pull_Direction.py
knit_graphs/Yarn.py
knit_graphs/__init__.py
knit_graphs/artin_wale_braids/Crossing_Direction.py
knit_graphs/artin_wale_braids/Loop_Braid_Graph.py
knit_graphs/artin_wale_braids/Wale.py
knit_graphs/artin_wale_braids/Wale_Braid.py
knit_graphs/artin_wale_braids/Wale_Braid_Word.py
knit_graphs/artin_wale_braids/Wale_Group.py
knit_graphs/artin_wale_braids/__init__.py
knit_graphs/basic_knit_graph_generators.py
knit_graphs-0.0.10.dist-info/LICENSE
knit_graphs-0.0.10.dist-info/METADATA
knit_graphs-0.0.10.dist-info/WHEEL
knit_graphs-0.0.10.dist-info/RECORD
