Metadata-Version: 2.1
Name: knit-graphs
Version: 0.0.10
Summary: A graph representation of knitted structures where each loop is a node and edges represent yarn and stitch relationships.
Home-page: https://mhofmann-khoury.github.io/knit_graph/
License: MIT
Keywords: ACT Lab,Northeastern University,knit,machine knit,fabrication,textile
Author: Megan Hofmann
Author-email: m.hofmann@northeastern.edu
Maintainer: Megan Hofmann
Maintainer-email: m.hofmann@northeastern.edu
Requires-Python: >=3.11,<3.14
Classifier: Development Status :: 3 - Alpha
Classifier: Intended Audience :: Developers
Classifier: License :: OSI Approved :: MIT License
Classifier: Natural Language :: English
Classifier: Operating System :: OS Independent
Classifier: Programming Language :: Python :: 3
Classifier: Programming Language :: Python :: 3.11
Classifier: Programming Language :: Python :: 3.12
Classifier: Programming Language :: Python :: 3.13
Classifier: Topic :: Scientific/Engineering
Requires-Dist: networkx (>=3.5)
Requires-Dist: plotly (>=6.3.0,<7.0.0)
Project-URL: Documentation, https://mhofmann-khoury.github.io/knit_graph/
Project-URL: Repository, https://github.com/mhofmann-Khoury/knit_graph/
